pass_manager_ch/__init__.py
pass_manager_ch/main.py
pass_manager_ch-0.1.2.dist-info/METADATA
pass_manager_ch-0.1.2.dist-info/WHEEL
pass_manager_ch-0.1.2.dist-info/entry_points.txt
pass_manager_ch-0.1.2.dist-info/RECORD
