Metadata-Version: 2.1
Name: pass-manager-ch
Version: 0.1.2
Summary: 
Author: oscar.bahamonde.ext
Author-email: oscar.bahamonde.ext@holcim.com
Requires-Python: >=3.10,<4.0
Classifier: Programming Language :: Python :: 3
Classifier: Programming Language :: Python :: 3.10
Classifier: Programming Language :: Python :: 3.11
Classifier: Programming Language :: Python :: 3.12
Requires-Dist: click (>=8.1.7,<9.0.0)
Requires-Dist: rocksdict (>=0.3.23,<0.4.0)
